llm_gitbard/__init__.py
llm_gitbard/configs.py
llm_gitbard/git.py
llm_gitbard/gitbard.py
llm_gitbard/llm_hook.py
llm_gitbard/prompt.py
llm_gitbard-0.1.0.dist-info/METADATA
llm_gitbard-0.1.0.dist-info/WHEEL
llm_gitbard-0.1.0.dist-info/entry_points.txt
llm_gitbard-0.1.0.dist-info/top_level.txt
llm_gitbard-0.1.0.dist-info/RECORD
